helm/__init__.py
helm/_version.py
helm/commands.py
helm/common.py
helm/dependency.py
helm/get.py
helm/models.py
helm/plugin.py
helm/registry.py
helm/repo.py
helm/search.py
helm/show.py
helm_client-0.2.3.dist-info/METADATA
helm_client-0.2.3.dist-info/WHEEL
helm_client-0.2.3.dist-info/RECORD
